cd_multi_tasker/__init__.py
cd_multi_tasker/cd_multi_tasker.py
cd_multi_tasker/version.py
cd_multi_tasker-0.1.2.dist-info/LICENSE.md
cd_multi_tasker-0.1.2.dist-info/LICENSE.txt
cd_multi_tasker-0.1.2.dist-info/METADATA
cd_multi_tasker-0.1.2.dist-info/WHEEL
cd_multi_tasker-0.1.2.dist-info/RECORD
