Metadata-Version: 2.1
Name: cd-multi-tasker
Version: 0.1.2
Summary: A Python package for handling multiple concurrent tasks using multiprocessing and multithreading.
Home-page: https://codedocta.com
License: MIT
Author: Nicholas Capasso
Author-email: codedocta@gmail.com
Requires-Python: >=3.9,<4.0
Classifier: License :: OSI Approved :: MIT License
Classifier: Programming Language :: Python :: 3
Classifier: Programming Language :: Python :: 3.9
Classifier: Programming Language :: Python :: 3.10
Classifier: Programming Language :: Python :: 3.11
Classifier: Programming Language :: Python :: 3.12
Project-URL: Repository, https://github.com/codedocta/cd_multi_tasker
